[
    {
        "title": "Awareness Van at Indira Gandhi Stadium",
        "images": [
            "https://i.ibb.co/CW0mkJ0/image.jpg",
            "https://i.ibb.co/8Pm2MCn/2.jpg",
            "https://i.ibb.co/VL81F3q/3.jpg",
            "https://i.ibb.co/LS4S8zM/4.jpg",
            "https://i.ibb.co/S7GsDFZ/9.jpg",
            "https://i.ibb.co/PhK9fxT/10.jpg",
            "https://i.ibb.co/PQ5z7VZ/11.jpg",
            "https://i.ibb.co/QFzy03R/12.jpg",
            "https://i.ibb.co/vZDyM7x/13.jpg",
            "https://i.ibb.co/tqMRshs/16.jpg",
            "https://i.ibb.co/wRj4QXT/17.jpg",
            "https://i.ibb.co/qghqbFt/18.jpg",
            "https://i.ibb.co/sw6PSDD/21.jpg",
            "https://i.ibb.co/L5mfqVz/24.jpg",
            "https://i.ibb.co/SN22rPL/25.jpg",
            "https://i.ibb.co/3SmhQ3J/26.jpg",
            "https://i.ibb.co/Ss0sDsN/27.jpg"
        ]
    },
    {
        "title": "Posters",
        "images": [
            "https://i.ibb.co/1LCbktV/image.jpg",
            "https://i.ibb.co/DfTN7wD/1.jpg",
            "https://i.ibb.co/MkZT3rL/2.jpg"
        ]
    },
    {
        "title": "Voterhelpline app used by people",
        "images": [
            "https://i.ibb.co/fGf4g7b/2.jpg",
            "https://i.ibb.co/rfbyPLz/image.jpg",
            "https://i.ibb.co/qFLRQ4r/5.jpg",
            "https://i.ibb.co/0nxSRy9/6.jpg",
            "https://i.ibb.co/Bgk8Bp8/7.jpg"
        ]
    },
    {
        "title": "Awareness Van at Madhagadipet Market",
        "images": [
            "https://i.ibb.co/NnqHVJb/3.jpg",
            "https://i.ibb.co/qgKSwWy/image.jpg",
            "https://i.ibb.co/thBSjDB/4.jpg",
            "https://i.ibb.co/DVY7YR2/8.jpg",
            "https://i.ibb.co/R6nSWX8/10.jpg",
            "https://i.ibb.co/HFRn10S/13.jpg",
            "https://i.ibb.co/PghmGrG/17.jpg",
            "https://i.ibb.co/PcR1m6h/18.jpg",
            "https://i.ibb.co/m5K6xcS/19.jpg",
            "https://i.ibb.co/Hqpk0bM/20.jpg",
            "https://i.ibb.co/tbwNyxw/21.jpg",
            "https://i.ibb.co/k9Z7v12/22.jpg",
            "https://i.ibb.co/n07ZDSX/23.jpg",
            "https://i.ibb.co/Sc8fw8R/24.jpg"
        ]
    },
    {
        "title": "Awareness Van at SMVEC",
        "images": [
            "https://i.ibb.co/7jgYfwJ/image.jpg",
            "https://i.ibb.co/p07YFnK/2.jpg",
            "https://i.ibb.co/W3ycXZF/5.jpg",
            "https://i.ibb.co/R4n3RVt/12.jpg",
            "https://i.ibb.co/fnHBXnX/9.jpg",
            "https://i.ibb.co/Gs1cbVT/13.jpg",
            "https://i.ibb.co/82KST2h/16.jpg",
            "https://i.ibb.co/1qRWWtD/17.jpg",
            "https://i.ibb.co/WxPCRfT/20.jpg",
            "https://i.ibb.co/86KvPW6/22.jpg",
            "https://i.ibb.co/s6hmr7C/21.jpg",
            "https://i.ibb.co/y8Bymgz/23.jpg",
            "https://i.ibb.co/Y3kL7PM/24.jpg",
            "https://i.ibb.co/5WDx6b0/25.jpg",
            "https://i.ibb.co/7NrhV3p/26.jpg"
        ]
    },
    {
        "title": "Awareness Van at Uruvaiyar",
        "images": []
    },
    {
        "title": "Awareness Ballon 2017",
        "images": [
            "https://i.ibb.co/6ZTLyHK/4.jpg",
            "https://i.ibb.co/SKwTYd2/image.jpg",
            "https://i.ibb.co/L1P3jJ3/7.jpg",
            "https://i.ibb.co/MsF52mz/8.jpg",
            "https://i.ibb.co/RgMqC74/14.jpg",
            "https://i.ibb.co/N9jxfgR/16.jpg",
            "https://i.ibb.co/cvQDvKx/18.jpg",
            "https://i.ibb.co/NrqPXrK/21.jpg",
            "https://i.ibb.co/RhTkcbg/23.jpg",
            "https://i.ibb.co/KqNmzxh/26.jpg",
            "https://i.ibb.co/6vrwLzN/28.jpg",
            "https://i.ibb.co/KLz3Zmm/30.jpg",
            "https://i.ibb.co/d0Pdr0n/32.jpg",
            "https://i.ibb.co/JpZpZ8j/33.jpg",
            "https://i.ibb.co/8jVbQDb/36.jpg",
            "https://i.ibb.co/Qdp3fjj/38.jpg",
            "https://i.ibb.co/zG5RybX/40.jpg",
            "https://i.ibb.co/HVwkYtm/44.jpg",
            "https://i.ibb.co/smF9mxn/47.jpg",
            "https://i.ibb.co/4fDpZqg/48.jpg",
            "https://i.ibb.co/J59B8rF/49.jpg",
            "https://i.ibb.co/M8tPGgD/50.jpg",
            "https://i.ibb.co/xftbLzq/53.jpg",
            "https://i.ibb.co/PZp8JNQ/55.jpg",
            "https://i.ibb.co/fXYnVpk/56.jpg",
            "https://i.ibb.co/G245kdz/57.jpg",
            "https://i.ibb.co/6vGpjrj/60.jpg",
            "https://i.ibb.co/xHzZ69D/61.jpg",
            "https://i.ibb.co/71bwYCG/64.jpg",
            "https://i.ibb.co/3dsRcy3/66.jpg",
            "https://i.ibb.co/NjgR9BB/69.jpg",
            "https://i.ibb.co/JBBGbjq/70.jpg",
            "https://i.ibb.co/wB7pb4K/78.jpg",
            "https://i.ibb.co/FxDV9qJ/80.jpg",
            "https://i.ibb.co/GdMqhVY/81.jpg",
            "https://i.ibb.co/bJ1bwxb/82.jpg",
            "https://i.ibb.co/gMzLfwH/85.jpg",
            "https://i.ibb.co/kJDLRXp/86.jpg",
            "https://i.ibb.co/qB3GB12/88.jpg",
            "https://i.ibb.co/F8ZPfZ6/image.jpg",
            "https://i.ibb.co/wC9B06h/",
            "https://i.ibb.co/DzpkPc8/2.jpg",
            "https://i.ibb.co/jyCsWZH/3.jpg",
            "https://i.ibb.co/7j1qxGy/4.jpg"
        ]
    },
    {
        "title": "Banners on Streets",
        "images": [
            "https://i.ibb.co/pv8ps2M/3.jpg",
            "https://i.ibb.co/qCtrzXh/8.jpg",
            "https://i.ibb.co/nQRVPRW/9.jpg",
            "https://i.ibb.co/rvyr3FQ/11.jpg",
            "https://i.ibb.co/YW7qHrz/13.jpg",
            "https://i.ibb.co/rs2m7Bx/14.jpg",
            "https://i.ibb.co/Rgw7rCK/15.jpg",
            "https://i.ibb.co/bJX4FN4/20.jpg",
            "https://i.ibb.co/09ZfK2m/22.jpg",
            "https://i.ibb.co/xGQyS3h/26.jpg",
            "https://i.ibb.co/zJzF0VF/28.jpg",
            "https://i.ibb.co/3d9Jn6Q/29.jpg",
            "https://i.ibb.co/2yMJjpy/30.jpg",
            "https://i.ibb.co/87WP0cy/31.jpg",
            "https://i.ibb.co/s9PfxVd/32.jpg",
            "https://i.ibb.co/p1VZVjr/33.jpg",
            "https://i.ibb.co/hX6WNPc/34.jpg",
            "https://i.ibb.co/fxnFx3w/39.jpg",
            "https://i.ibb.co/gZbJBQq/40.jpg",
            "https://i.ibb.co/brKysDW/41.jpg",
            "https://i.ibb.co/QmvZcMK/48.jpg",
            "https://i.ibb.co/1Q2Fjcc/49.jpg",
            "https://i.ibb.co/s3x7NSK/50.jpg",
            "https://i.ibb.co/nQ9hWyK/52.jpg",
            "https://i.ibb.co/P650nNX/53.jpg",
            "https://i.ibb.co/Lz20JDX/54.jpg",
            "https://i.ibb.co/M7cxY7b/58.jpg",
            "https://i.ibb.co/9YRzRSD/60.jpg"
        ]
    },
    {
        "title": "Awareness Van at PG college",
        "images": [
            "https://i.ibb.co/Wk1bvXZ/3.jpg",
            "https://i.ibb.co/0jXJdwp/1.jpg",
            "https://i.ibb.co/q04dYW2/5.jpg",
            "https://i.ibb.co/vZyFrGD/7.jpg",
            "https://i.ibb.co/Gd9K5vj/10.jpg",
            "https://i.ibb.co/8M4JyYN/14.jpg",
            "https://i.ibb.co/2gf5LpW/20.jpg",
            "https://i.ibb.co/4RK90Cg/21.jpg",
            "https://i.ibb.co/f4bzgZ5/24.jpg",
            "https://i.ibb.co/HxgHGBz/28.jpg",
            "https://i.ibb.co/VTgWynV/30.jpg",
            "https://i.ibb.co/h9VQ9d4/31.jpg",
            "https://i.ibb.co/8r9Xr45/34.jpg",
            "https://i.ibb.co/LN6k3Wf/35.jpg",
            "https://i.ibb.co/MC25zKM/39.jpg",
            "https://i.ibb.co/fQtpf7j/40.jpg",
            "https://i.ibb.co/j8X5rGt/43.jpg",
            "https://i.ibb.co/2Pc0F01/44.jpg",
            "https://i.ibb.co/5MS52wS/45.jpg",
            "https://i.ibb.co/gwkZfMK/47.jpg",
            "https://i.ibb.co/vH4P35w/51.jpg",
            "https://i.ibb.co/JKmJrxF/54.jpg",
            "https://i.ibb.co/jW01jLx/55.jpg",
            "https://i.ibb.co/MMCQFDs/56.jpg",
            "https://i.ibb.co/db4ypWh/59.jpg",
            "https://i.ibb.co/VL6gqR4/61.jpg",
            "https://i.ibb.co/tzprBrZ/66.jpg",
            "https://i.ibb.co/NWtLgWD/69.jpg",
            "https://i.ibb.co/G2PDhgS/73.jpg",
            "https://i.ibb.co/6BR0zFk/77.jpg",
            "https://i.ibb.co/DRcjQpX/78.jpg",
            "https://i.ibb.co/XZhRR6V/79.jpg",
            "https://i.ibb.co/4KFmTpG/81.jpg",
            "https://i.ibb.co/SV0PSBG/82.jpg",
            "https://i.ibb.co/BgPHWLX/86.jpg",
            "https://i.ibb.co/LRkpJ5Y/87.jpg",
            "https://i.ibb.co/kG5LKjg/88.jpg",
            "https://i.ibb.co/vVbksmc/92.jpg",
            "https://i.ibb.co/3dQmDn2/98.jpg",
            "https://i.ibb.co/QJdxrTV/102.jpg",
            "https://i.ibb.co/Wk1bvXZ/3.jpg",
            "https://i.ibb.co/0jXJdwp/1.jpg",
            "https://i.ibb.co/q04dYW2/5.jpg",
            "https://i.ibb.co/vZyFrGD/7.jpg",
            "https://i.ibb.co/Gd9K5vj/10.jpg",
            "https://i.ibb.co/8M4JyYN/14.jpg",
            "https://i.ibb.co/2gf5LpW/20.jpg",
            "https://i.ibb.co/4RK90Cg/21.jpg",
            "https://i.ibb.co/f4bzgZ5/24.jpg",
            "https://i.ibb.co/HxgHGBz/28.jpg",
            "https://i.ibb.co/VTgWynV/30.jpg",
            "https://i.ibb.co/h9VQ9d4/31.jpg",
            "https://i.ibb.co/8r9Xr45/34.jpg",
            "https://i.ibb.co/LN6k3Wf/35.jpg",
            "https://i.ibb.co/MC25zKM/39.jpg",
            "https://i.ibb.co/fQtpf7j/40.jpg",
            "https://i.ibb.co/j8X5rGt/43.jpg",
            "https://i.ibb.co/2Pc0F01/44.jpg",
            "https://i.ibb.co/5MS52wS/45.jpg",
            "https://i.ibb.co/gwkZfMK/47.jpg",
            "https://i.ibb.co/vH4P35w/51.jpg",
            "https://i.ibb.co/JKmJrxF/54.jpg",
            "https://i.ibb.co/jW01jLx/55.jpg",
            "https://i.ibb.co/MMCQFDs/56.jpg",
            "https://i.ibb.co/db4ypWh/59.jpg",
            "https://i.ibb.co/VL6gqR4/61.jpg",
            "https://i.ibb.co/tzprBrZ/66.jpg",
            "https://i.ibb.co/NWtLgWD/69.jpg",
            "https://i.ibb.co/G2PDhgS/73.jpg",
            "https://i.ibb.co/6BR0zFk/77.jpg",
            "https://i.ibb.co/DRcjQpX/78.jpg",
            "https://i.ibb.co/XZhRR6V/79.jpg",
            "https://i.ibb.co/4KFmTpG/81.jpg",
            "https://i.ibb.co/SV0PSBG/82.jpg",
            "https://i.ibb.co/BgPHWLX/86.jpg",
            "https://i.ibb.co/LRkpJ5Y/87.jpg",
            "https://i.ibb.co/kG5LKjg/88.jpg",
            "https://i.ibb.co/vVbksmc/92.jpg",
            "https://i.ibb.co/3dQmDn2/98.jpg",
            "https://i.ibb.co/QJdxrTV/102.jpg"
        ]
    },
    {
        "title": "Awareness Van at Ramnathpuram School",
        "images": [
            "https://i.ibb.co/853GgbL/4.jpg",
            "https://i.ibb.co/JKSChmW/image.jpg",
            "https://i.ibb.co/1nzby5Z/7.jpg",
            "https://i.ibb.co/CnD9jr6/6.jpg",
            "https://i.ibb.co/cvQtsgk/8.jpg",
            "https://i.ibb.co/XWfqJC8/10.jpg",
            "https://i.ibb.co/n3bzYRD/12.jpg",
            "https://i.ibb.co/pwxHD7w/16.jpg",
            "https://i.ibb.co/jG8FLzZ/17.jpg",
            "https://i.ibb.co/F3dnfJr/18.jpg",
            "https://i.ibb.co/DrT8pvZ/19.jpg",
            "https://i.ibb.co/z63tJzR/20.jpg",
            "https://i.ibb.co/d4gmTRZ/21.jpg",
            "https://i.ibb.co/Ws5R29L/22.jpg",
            "https://i.ibb.co/R3YjbVM/23.jpg",
            "https://i.ibb.co/dQW8cY3/24.jpg",
            "https://i.ibb.co/crrfGZ8/25.jpg",
            "https://i.ibb.co/86CLFrb/27.jpg",
            "https://i.ibb.co/dQNzdw1/28.jpg",
            "https://i.ibb.co/bPBmCks/30.jpg",
            "https://i.ibb.co/2kyxHhT/31.jpg",
            "https://i.ibb.co/Kx03PLm/32.jpg",
            "https://i.ibb.co/SBDkrLF/33.jpg",
            "https://i.ibb.co/7GFVNY1/35.jpg",
            "https://i.ibb.co/G00xxjH/36.jpg",
            "https://i.ibb.co/3hNxrwd/37.jpg",
            "https://i.ibb.co/GJ6NybW/38.jpg"
        ]
    },
    {
        "title": "National Voters Day 2021",
        "images": [
            "https://i.ibb.co/LDwwt56/image.jpg",
            "https://i.ibb.co/t4W0JwT/1.jpg",
            "https://i.ibb.co/nPXY8nS/2.jpg",
            "https://i.ibb.co/4Tm4bP8/3.jpg",
            "https://i.ibb.co/VShXtNb/4.jpg",
            "https://i.ibb.co/8gXbxwT/5.jpg",
            "https://i.ibb.co/BgB9R8y/6.jpg",
            "https://i.ibb.co/Wp8YT85/7.jpg",
            "https://i.ibb.co/3WFd7Pt/8.jpg",
            "https://i.ibb.co/Hp48Lp0/9.jpg",
            "https://i.ibb.co/sRtVnZ4/10.jpg",
            "https://i.ibb.co/3m0fw1J/11.jpg",
            "https://i.ibb.co/JsF7Xkv/12.jpg",
            "https://i.ibb.co/Dzh7Q4W/13.jpg",
            "https://i.ibb.co/J20QJ4G/14.jpg",
            "https://i.ibb.co/L8kvybT/15.jpg",
            "https://i.ibb.co/1dvsBLd/16.jpg",
            "https://i.ibb.co/QFJDR1N/17.jpg",
            "https://i.ibb.co/YjyFvNN/18.jpg",
            "https://i.ibb.co/6DyxLRg/19.jpg",
            "https://i.ibb.co/NFRyJ2z/20.jpg",
            "https://i.ibb.co/cT9yWg2/21.jpg",
            "https://i.ibb.co/2jrkx7z/22.jpg",
            "https://i.ibb.co/tLr1Y0z/23.jpg",
            "https://i.ibb.co/g4F5MNX/24.jpg",
            "https://i.ibb.co/94CPdXR/25.jpg",
            "https://i.ibb.co/GVGBFcR/26.jpg",
            "https://i.ibb.co/t44SbnK/27.jpg",
            "https://i.ibb.co/2gzCBwT/28.jpg",
            "https://i.ibb.co/4NzgG1y/29.jpg",
            "https://i.ibb.co/CmzbVRB/30.jpg",
            "https://i.ibb.co/0BWb1M8/31.jpg",
            "ttps://i.ibb.co/nQRGjLP/60.jpg",
            "https://i.ibb.co/0VWLtDq/61.jpg",
            "https://i.ibb.co/nM7Xyxn/62.jpg",
            "https://i.ibb.co/3hDDnFv/63.jpg",
            "https://i.ibb.co/HKKMBWh/64.jpg",
            "https://i.ibb.co/k3sw6b1/65.jpg",
            "https://i.ibb.co/31WFCTw/66.jpg",
            "https://i.ibb.co/g7HtqDC/67.jpg",
            "https://i.ibb.co/vCF7MBy/68.jpg",
            "https://i.ibb.co/D4xbL0r/69.jpg",
            "https://i.ibb.co/YphyP1X/70.jpg",
            "https://i.ibb.co/tb2VNDd/71.jpg",
            "https://i.ibb.co/DwKgTqF/72.jpg",
            "https://i.ibb.co/JprsKxM/73.jpg",
            "https://i.ibb.co/ZmVjtV8/74.jpg",
            "https://i.ibb.co/nL5kbgg/75.jpg",
            "https://i.ibb.co/XZK8kZ9/76.jpg",
            "https://i.ibb.co/Wg6KJZR/77.jpg",
            "https://i.ibb.co/YyWzcwT/79.jpg",
            "https://i.ibb.co/4sDxrf5/290.jpg",
            "https://i.ibb.co/28fN08C/291.jpg",
            "https://i.ibb.co/G2XwZXp/292.jpg",
            "https://i.ibb.co/3fZFzNk/293.jpg",
            "https://i.ibb.co/p15j6cc/295.jpg",
            "https://i.ibb.co/n6SdgWK/296.jpg",
            "https://i.ibb.co/dk4hVXc/297.jpg",
            "https://i.ibb.co/tQ1GmF5/298.jpg",
            "https://i.ibb.co/WtdwZv8/175.jpg",
            "https://i.ibb.co/8m3BxPw/176.jpg",
            "https://i.ibb.co/XsZqT6h/177.jpg",
            "https://i.ibb.co/HBbs733/178.jpg",
            "https://i.ibb.co/fSjJZqq/179.jpg",
            "https://i.ibb.co/y4mkdFg/183.jpg",
            "https://i.ibb.co/C55V7sQ/201.jpg",
            "https://i.ibb.co/2cZ0pSb/202.jpg",
            "https://i.ibb.co/2ktDV0n/203.jpg",
            "https://i.ibb.co/rQhhdm1/194.jpg",
            "https://i.ibb.co/dmbcpfw/195.jpg",
            "https://i.ibb.co/0nfMvQJ/196.jpg",
            "https://i.ibb.co/fHjKDFW/197.jpg",
            "https://i.ibb.co/bsfztRH/198.jpg",
            "https://i.ibb.co/Q9VMZTp/199.jpg",
            "https://i.ibb.co/Kx63DRd/200.jpg"
        ]
    },
    {
        "title": "Physically Challenged persons Cricket",
        "images": [
            "https://i.ibb.co/MB2NLYz/image.jpg",
            "https://i.ibb.co/HKtjpsn/1.jpg",
            "https://i.ibb.co/TWpvrKX/2.jpg",
            "https://i.ibb.co/N2HFY2c/4.jpg",
            "https://i.ibb.co/VSXBFff/8.jpg",
            "https://i.ibb.co/7YqHYTF/9.jpg",
            "https://i.ibb.co/7RnDCtj/12.jpg",
            "https://i.ibb.co/xs4zcBJ/13.jpg",
            "https://i.ibb.co/2jpfKq3/14.jpg",
            "https://i.ibb.co/LgvxqR6/15.jpg",
            "https://i.ibb.co/1LDt0D8/18.jpg",
            "https://i.ibb.co/MgDD7ZV/19.jpg",
            "https://i.ibb.co/1rjyYM4/20.jpg",
            "https://i.ibb.co/wJkjx0m/21.jpg",
            "https://i.ibb.co/m8k8ksJ/22.jpg",
            "https://i.ibb.co/1LCVgw6/23.jpg",
            "https://i.ibb.co/8N5rfr7/24.jpg",
            "https://i.ibb.co/R4LgxbK/25.jpg",
            "https://i.ibb.co/ZLL9snL/26.jpg",
            "https://i.ibb.co/RzTmDPC/27.jpg",
            "https://i.ibb.co/cLdcMJF/28.jpg",
            "https://i.ibb.co/1rkmSgT/29.jpg",
            "https://i.ibb.co/4jdNLVx/30.jpg",
            "https://i.ibb.co/Vjgr29r/31.jpg",
            "https://i.ibb.co/3zNSW7y/32.jpg",
            "https://i.ibb.co/g3Yrfgy/33.jpg",
            "https://i.ibb.co/KhxK72C/34.jpg",
            "https://i.ibb.co/WPBf6LJ/35.jpg"
        ]
    },
    {
        "title": "Voters Van",
        "images": [
            "https://i.ibb.co/BsstNS1/3.jpg",
            "https://i.ibb.co/PjxZCjJ/1.jpg",
            "https://i.ibb.co/9WR7C3F/4.jpg",
            "https://i.ibb.co/wQRzNtS/5.jpg",
            "https://i.ibb.co/JnrwtqW/6.jpg",
            "https://i.ibb.co/zsB5ZSG/7.jpg",
            "https://i.ibb.co/fdY2z6d/8.jpg",
            "https://i.ibb.co/McRGVqk/10.jpg",
            "https://i.ibb.co/pJ9qkwZ/11.jpg",
            "https://i.ibb.co/KxmjMN2/12.jpg",
            "https://i.ibb.co/51GCyny/13.jpg",
            "https://i.ibb.co/cT3NRr9/14.jpg",
            "https://i.ibb.co/TTrGq02/15.jpg",
            "https://i.ibb.co/rvbqrmR/16.jpg",
            "https://i.ibb.co/pRMBzFV/17.jpg",
            "https://i.ibb.co/8Nx8DNw/18.jpg",
            "https://i.ibb.co/6Np6Gpm/19.jpg",
            "https://i.ibb.co/0hCLQsx/20.jpg",
            "https://i.ibb.co/VtKBym2/21.jpg",
            "https://i.ibb.co/BBR7XRy/22.jpg"
        ]
    },
    {
        "title": "Inaugration of Voters Van",
        "images": [
            "https://i.ibb.co/JkcKd6w/image.jpg",
            "https://i.ibb.co/7Ks2nDh/2.jpg",
            "https://i.ibb.co/Mks8b1N/6.jpg",
            "https://i.ibb.co/QKBp7M6/9.jpg",
            "https://i.ibb.co/SNXM9LF/10.jpg",
            "https://i.ibb.co/g9ybFtv/16.jpg",
            "https://i.ibb.co/CQkxX98/19.jpg",
            "https://i.ibb.co/LvQz0Hv/20.jpg",
            "https://i.ibb.co/Lg17mpH/22.jpg",
            "https://i.ibb.co/4Fsc9bM/23.jpg",
            "https://i.ibb.co/TbRyhPH/24.jpg",
            "https://i.ibb.co/pXr1fRC/25.jpg",
            "https://i.ibb.co/fp40Tpx/26.jpg",
            "https://i.ibb.co/MfSyZmN/27.jpg",
            "https://i.ibb.co/jhQJwNp/28.jpg",
            "https://i.ibb.co/xHLQYQ9/29.jpg",
            "https://i.ibb.co/2jYF2Sk/30.jpg",
            "https://i.ibb.co/TMYXnq0/36.jpg",
            "https://i.ibb.co/KWRL9W2/37.jpg",
            "https://i.ibb.co/cgbYhYT/38.jpg",
            "https://i.ibb.co/jyjZF5D/41.jpg",
            "https://i.ibb.co/KFCt3QD/42.jpg",
            "https://i.ibb.co/Jq6R5cZ/43.jpg",
            "https://i.ibb.co/1sXSh1y/44.jpg",
            "https://i.ibb.co/8MYvRMG/45.jpg",
            "https://i.ibb.co/12C0CRz/47.jpg",
            "https://i.ibb.co/vkzgJvk/48.jpg"
        ]
    }
]